rtmps/__init__.py
rtmps/__main__.py
rtmps/cli.py
rtmps/client.py
rtmps/ffmpeg.py
rtmps/handlers.py
rtmps/player.py
rtmps/storage.py
rtmps/utils.py
rtmps/watcher.py
rtmps-0.1.1.dist-info/licenses/LICENSE
rtmps-0.1.1.dist-info/METADATA
rtmps-0.1.1.dist-info/WHEEL
rtmps-0.1.1.dist-info/entry_points.txt
rtmps-0.1.1.dist-info/top_level.txt
rtmps-0.1.1.dist-info/RECORD
