Metadata-Version: 2.4
Name: rtmps
Version: 0.1.1
Summary: Telegram RTMPS Voice Chat music streaming engine (educational, non-commercial)
Home-page: https://github.com/ankit-chaubey/rtmps
Author: Ankit Chaubey
Author-email: 
Project-URL: Source, https://github.com/ankit-chaubey/rtmps
Project-URL: Bug Tracker, https://github.com/ankit-chaubey/rtmps/issues
Project-URL: Documentation, https://github.com/ankit-chaubey/rtmps#readme
Keywords: telegram,voice-chat,music-bot,rtmps,ffmpeg,telethon,streaming,education,non-commercial
Classifier: Development Status :: 4 - Beta
Classifier: Intended Audience :: Developers
Classifier: Intended Audience :: Education
Classifier: Topic :: Multimedia :: Sound/Audio :: Players
Classifier: Topic :: Communications :: Chat
Classifier: Programming Language :: Python :: 3
Classifier: Programming Language :: Python :: 3 :: Only
Classifier: License :: Other/Proprietary License
Classifier: Operating System :: OS Independent
Requires-Python: >=3.8
License-File: LICENSE
Requires-Dist: telethon>=1.42.0
Requires-Dist: vasu>=0.1.0
Provides-Extra: speed
Requires-Dist: cryptg>=0.5.2; extra == "speed"
Dynamic: author
Dynamic: classifier
Dynamic: description
Dynamic: description-content-type
Dynamic: home-page
Dynamic: keywords
Dynamic: license-file
Dynamic: project-url
Dynamic: provides-extra
Dynamic: requires-dist
Dynamic: requires-python
Dynamic: summary
